{"mode":"playing","score":550,"wave":1,"lives":3,"player":{"x":240,"y":650,"w":34,"h":18},"bullets":[{"x":240,"y":406,"vy":-380}],"enemies":[{"id":0,"x":104,"y":108,"alive":true,"diving":false,"row":0,"col":0},{"id":1,"x":146,"y":108,"alive":true,"diving":false,"row":0,"col":1},{"id":2,"x":188,"y":108,"alive":true,"diving":false,"row":0,"col":2},{"id":3,"x":230,"y":108,"alive":true,"diving":false,"row":0,"col":3},{"id":4,"x":272,"y":108,"alive":true,"diving":false,"row":0,"col":4},{"id":5,"x":314,"y":108,"alive":true,"diving":false,"row":0,"col":5},{"id":6,"x":356,"y":108,"alive":true,"diving":false,"row":0,"col":6},{"id":7,"x":398,"y":108,"alive":true,"diving":false,"row":0,"col":7},{"id":8,"x":104,"y":144,"alive":true,"diving":false,"row":1,"col":0},{"id":9,"x":146,"y":144,"alive":true,"diving":false,"row":1,"col":1},{"id":10,"x":188,"y":144,"alive":true,"diving":false,"row":1,"col":2},{"id":11,"x":230,"y":144,"alive":true,"diving":false,"row":1,"col":3},{"id":12,"x":272,"y":144,"alive":true,"diving":false,"row":1,"col":4},{"id":13,"x":314,"y":144,"alive":true,"diving":false,"row":1,"col":5},{"id":14,"x":356,"y":144,"alive":true,"diving":false,"row":1,"col":6},{"id":15,"x":398,"y":144,"alive":true,"diving":false,"row":1,"col":7},{"id":16,"x":104,"y":180,"alive":true,"diving":false,"row":2,"col":0},{"id":17,"x":146,"y":180,"alive":true,"diving":false,"row":2,"col":1},{"id":18,"x":188,"y":180,"alive":true,"diving":false,"row":2,"col":2},{"id":19,"x":230,"y":180,"alive":true,"diving":false,"row":2,"col":3},{"id":20,"x":272,"y":180,"alive":true,"diving":false,"row":2,"col":4},{"id":21,"x":303,"y":357,"alive":false,"diving":true,"row":2,"col":5},{"id":22,"x":356,"y":180,"alive":true,"diving":false,"row":2,"col":6},{"id":23,"x":398,"y":180,"alive":true,"diving":false,"row":2,"col":7},{"id":24,"x":104,"y":216,"alive":true,"diving":false,"row":3,"col":0},{"id":25,"x":146,"y":216,"alive":true,"diving":false,"row":3,"col":1},{"id":26,"x":188,"y":216,"alive":true,"diving":false,"row":3,"col":2},{"id":27,"x":255,"y":216,"alive":false,"diving":false,"row":3,"col":3},{"id":28,"x":290,"y":198,"alive":false,"diving":false,"row":3,"col":4},{"id":29,"x":314,"y":216,"alive":true,"diving":false,"row":3,"col":5},{"id":30,"x":356,"y":216,"alive":true,"diving":false,"row":3,"col":6},{"id":31,"x":398,"y":216,"alive":true,"diving":false,"row":3,"col":7},{"id":32,"x":104,"y":252,"alive":true,"diving":false,"row":4,"col":0},{"id":33,"x":146,"y":252,"alive":true,"diving":false,"row":4,"col":1},{"id":34,"x":188,"y":252,"alive":true,"diving":false,"row":4,"col":2},{"id":35,"x":255,"y":234,"alive":false,"diving":false,"row":4,"col":3},{"id":36,"x":310,"y":252,"alive":false,"diving":false,"row":4,"col":4},{"id":37,"x":314,"y":252,"alive":true,"diving":false,"row":4,"col":5},{"id":38,"x":356,"y":252,"alive":true,"diving":false,"row":4,"col":6},{"id":39,"x":398,"y":252,"alive":true,"diving":false,"row":4,"col":7}],"formationDir":-1,"diveTimer":1.63,"lastDiveEnemyId":21,"hitsTaken":0,"seed":20260223,"coordinateSystem":{"origin":"top-left","x":"right","y":"down","units":"pixels"}}